[
    {
        "id": "hero_julius_caesar",
        "name": "Julio César",
        "lore": "Un brillante estratega militar y líder carismático. Bajo su mando, la legión romana alcanzó su máximo esplendor táctico.",
        "avatarAssetPath": "assets/images/heroes/caesar.png",
        "globalBonuses": [
            {
                "description": "Las tropas se crean un 10% más lento",
                "affectedStat": "training_speed",
                "multiplier": 1.10
            },
            {
                "description": "El costo de las unidades se reduce un 15%",
                "affectedStat": "unit_cost",
                "multiplier": 0.85
            },
            {
                "description": "Los recolectores trabajan +10% más rápido",
                "affectedStat": "gathering_speed",
                "multiplier": 1.10
            }
        ],
        "uniqueUnits": [
            "cavalry_julio_cesar"
        ],
        "heroUnitId": "hero_julius_caesar_unit"
    },
    {
        "id": "hero_scipio",
        "name": "Escipión el Africano",
        "lore": "Héroe de la Segunda Guerra Púnica, famoso por su victoria en Zama.",
        "avatarAssetPath": "assets/images/heroes/scipio.png",
        "globalBonuses": [
            {
                "description": "Ataque de caballería +20%",
                "affectedStat": "cavalry_attack",
                "multiplier": 1.20
            }
        ],
        "uniqueUnits": [],
        "heroUnitId": "hero_scipio_unit"
    },
    {
        "id": "hero_agrippa",
        "name": "Marco Vipsanio Agripa",
        "lore": "Leal arquitecto y general naval, clave en la formación del Imperio Romano.",
        "avatarAssetPath": "assets/images/heroes/agrippa.png",
        "globalBonuses": [
            {
                "description": "Velocidad de barcos +25%",
                "affectedStat": "ship_speed",
                "multiplier": 1.25
            }
        ],
        "uniqueUnits": [],
        "heroUnitId": "hero_agrippa_unit"
    }
]